openepda/__init__.py
openepda/black_box.py
openepda/expr.py
openepda/geometry.py
openepda/imports.py
openepda/main.py
openepda/updk.py
openepda/validators.py
openepda/schemas/cdf_schema_v0.1.yaml
openepda/schemas/cdf_schema_v0.2.yaml
openepda/schemas/cdf_schema_v0.3.yaml
openepda/schemas/gds_mapping_v0.1.yaml
openepda/schemas/gds_mapping_v0.2.yaml
openepda/schemas/pin_info_v0.1.yaml
openepda/schemas/updk_sbb_schema_v0.2.yaml
openepda/schemas/updk_sbb_schema_v0.3.yaml
openepda/schemas/updk_sbb_schema_v0.4.yaml
tests/__init__.py
tests/test_validators.py
openepda-0.1.20.dist-info/AUTHORS
openepda-0.1.20.dist-info/LICENSE
openepda-0.1.20.dist-info/METADATA
openepda-0.1.20.dist-info/WHEEL
openepda-0.1.20.dist-info/top_level.txt
openepda-0.1.20.dist-info/RECORD
