Metadata-Version: 2.1
Name: openepda
Version: 0.1.20
Summary: Implementation of open standards for electronic-photonic design automation
Home-page: http://openepda.org
Author: Dzmitry Pustakhod
Author-email: d.pustakhod@tue.nl
License: UNKNOWN
Keywords: EPDA data science electronics photonics design automation standard CAD PDA PIC
Platform: UNKNOWN
Classifier: Development Status :: 4 - Beta
Classifier: Intended Audience :: Science/Research
Classifier: Operating System :: OS Independent
Classifier: Programming Language :: Python
Classifier: Programming Language :: Python :: 3
Classifier: Programming Language :: Python :: 3 :: Only
Classifier: Programming Language :: Python :: 3.8
Classifier: Programming Language :: Python :: 3.9
Classifier: Programming Language :: Python :: 3.10
Classifier: Topic :: Scientific/Engineering
Classifier: Topic :: Software Development :: Libraries
License-File: LICENSE
License-File: AUTHORS
Requires-Dist: jsonschema
Requires-Dist: numpy
Requires-Dist: scipy
Requires-Dist: ruamel.yaml
Requires-Dist: pandas
Requires-Dist: more-itertools (>=8.2.0)
Requires-Dist: tatsu (>=4.4.0)
Requires-Dist: importlib-metadata ; python_version < "3.8"
